Metadata-Version: 2.1
Name: odoo13-addon-l10n-ro-stock-report
Version: 13.0.1.3.0
Summary: Romania - Stock Report
Home-page: https://github.com/OCA/l10n-romania
Author: Terrabit,NextERP Romania,Odoo Community Association (OCA)
Author-email: support@odoo-community.org
License: AGPL-3
Platform: UNKNOWN
Classifier: Programming Language :: Python
Classifier: Framework :: Odoo
Classifier: License :: OSI Approved :: GNU Affero General Public License v3
Requires-Python: >=3.5
Requires-Dist: odoo13-addon-date-range
Requires-Dist: odoo13-addon-l10n-ro-stock-account
Requires-Dist: odoo (<13.1dev,>=13.0a)
